<?xml version="1.0" encoding="UTF-8"?> <a:feed xmlns:a="http://www.w3.org/2005/Atom" xmlns="http://marketplace.xboxlive.com/resource/product/v1"><a:author><a:name>Xbox LIVE</a:name></a:author><a:id>http://marketplace.xboxlive.com/resource/product/v1</a:id><a:title>Query Result</a:title><a:updated>2024-07-21 23:34:48Z</a:updated><totalItems>1</totalItems><numItems>1</numItems><locale>en-US</locale><a:entry itemNum="1" xmlns:a="http://www.w3.org/2005/Atom" xmlns="http://marketplace.xboxlive.com/resource/product/v1"><a:title>Movistar Imagenio</a:title><a:id>urn:uuid:66acd000-77fe-1000-9115-d802423707d1</a:id><a:updated>2015-09-22T09:00:08.940Z</a:updated><a:content>game content</a:content><productType>61</productType><reducedTitle>Movistar Imagenio</reducedTitle><reducedDescription>Download this app</reducedDescription><fullTitle>Movistar Imagenio</fullTitle><fullDescription>Download this app</fullDescription><voiceDisplayTitle>Movistar Imagenio</voiceDisplayTitle><visibilityDate>2011-09-13T00:00:00</visibilityDate><globalOriginalReleaseDate>2011-12-06T00:00:00</globalOriginalReleaseDate><ratingId>0</ratingId><developerName>Telefónica S.A.</developerName><publisherName>Telefónica S.A.</publisherName><titleId>1110902737</titleId><hexTitleId>0x423707d1</hexTitleId><images><image><imageMediaId>4B92C938-8FB0-4C33-89BE-6FA932C5B9A4</imageMediaId><imageMediaInstanceId>D3FA852E-1365-4DFC-98FB-417FD411E675</imageMediaInstanceId><imageMediaType>14</imageMediaType><relationshipType>22</relationshipType><format>5</format><size>44</size><fileUrl>http://download.xbox.com/content/images/66acd000-77fe-1000-9115-d802423707d1/1033/tvposterlg.png</fileUrl><parentGameMediaId>66ACD000-77FE-1000-9115-D802423707D1</parentGameMediaId></image><image><imageMediaId>E536E954-2472-4D07-81DC-72B12FFC66A5</imageMediaId><imageMediaInstanceId>0DE3A5EA-F2EF-46D2-8ADB-4C8350CB624B</imageMediaInstanceId><imageMediaType>14</imageMediaType><relationshipType>23</relationshipType><format>5</format><size>14</size><fileUrl>http://download.xbox.com/content/images/66acd000-77fe-1000-9115-d802423707d1/1033/tile.png</fileUrl><parentGameMediaId>66ACD000-77FE-1000-9115-D802423707D1</parentGameMediaId></image><image><imageMediaId>7E8480D5-4DF2-466C-BDEA-6ABF102EC5EE</imageMediaId><imageMediaInstanceId>C19A87B6-03D1-4B14-92D8-53E8E9B34195</imageMediaInstanceId><imageMediaType>14</imageMediaType><relationshipType>33</relationshipType><format>5</format><size>25</size><fileUrl>http://download.xbox.com/content/images/423707D1/en-us/tvposterlg.png</fileUrl><parentGameMediaId>66ACD000-77FE-1000-9115-D802423707D1</parentGameMediaId></image><image><imageMediaId>EE8523E6-9FEC-41C4-B0C3-CE13783A22B4</imageMediaId><imageMediaInstanceId>07665BD0-111C-4BE1-99E3-7F3551EC0392</imageMediaInstanceId><imageMediaType>14</imageMediaType><relationshipType>33</relationshipType><format>4</format><size>23</size><fileUrl>http://download.xbox.com/content/images/66acd000-77fe-1000-9115-d802423707d1/1033/boxartlg.jpg</fileUrl><parentGameMediaId>66ACD000-77FE-1000-9115-D802423707D1</parentGameMediaId></image><image><imageMediaId>AB608EE4-F832-45C8-BDF1-41636A16C9DA</imageMediaId><imageMediaInstanceId>6F532B9F-7802-42C0-8C5F-8EA84DB8ADD8</imageMediaInstanceId><imageMediaType>14</imageMediaType><relationshipType>33</relationshipType><format>4</format><size>46</size><fileUrl>http://download.xbox.com/content/images/66acd000-77fe-1000-9115-d802423707d1/1033/providerlogo.jpg</fileUrl><parentGameMediaId>66ACD000-77FE-1000-9115-D802423707D1</parentGameMediaId></image><image><imageMediaId>9E6C8FED-1BCB-4AAF-842A-5B2FF76DDD2E</imageMediaId><imageMediaInstanceId>9EF15E96-F7CC-4C48-A9F1-B727FC947AD1</imageMediaInstanceId><imageMediaType>14</imageMediaType><relationshipType>25</relationshipType><format>4</format><size>22</size><fileUrl>http://download.xbox.com/content/images/66acd000-77fe-1000-9115-d802423707d1/1033/background.jpg</fileUrl><parentGameMediaId>66ACD000-77FE-1000-9115-D802423707D1</parentGameMediaId></image><image><imageMediaId>CCF1DAB3-57D7-4A74-A70E-B552FC84B2E4</imageMediaId><imageMediaInstanceId>7643B6A1-C482-4CF5-9E78-C32EB78D835C</imageMediaInstanceId><imageMediaType>14</imageMediaType><relationshipType>33</relationshipType><format>4</format><size>30</size><fileUrl>http://download.xbox.com/content/images/66acd000-77fe-1000-9115-d802423707d1/1033/boxartsm.jpg</fileUrl><parentGameMediaId>66ACD000-77FE-1000-9115-D802423707D1</parentGameMediaId></image><image><imageMediaId>B66B3E07-C39D-4948-A3F8-C4D08DC9AB4C</imageMediaId><imageMediaInstanceId>D03AEB6A-B596-4807-82E5-DF807D15EF34</imageMediaInstanceId><imageMediaType>14</imageMediaType><relationshipType>33</relationshipType><format>5</format><size>45</size><fileUrl>http://download.xbox.com/content/images/423707D1/en-us/tvpostersm.png</fileUrl><parentGameMediaId>66ACD000-77FE-1000-9115-D802423707D1</parentGameMediaId></image><image><imageMediaId>294B1916-3A03-48D1-A930-9C16A8F45807</imageMediaId><imageMediaInstanceId>AB750A4C-CC68-473E-9476-E6284966BC88</imageMediaInstanceId><imageMediaType>14</imageMediaType><relationshipType>27</relationshipType><format>5</format><size>15</size><fileUrl>http://download.xbox.com/content/images/66acd000-77fe-1000-9115-d802423707d1/1033/banner.png</fileUrl><parentGameMediaId>66ACD000-77FE-1000-9115-D802423707D1</parentGameMediaId></image></images><slideShows><slideShow><image><displayOrder>1</displayOrder><imageMediaId>2AE279B0-83AD-48F2-881D-055724516A1C</imageMediaId><imageMediaInstanceId>C4B16602-02A6-4141-9F9B-8CF9252EC012</imageMediaInstanceId><imageMediaType>14</imageMediaType><relationshipType>32</relationshipType><format>4</format><size>27</size><fileUrl>http://download.xbox.com/content/images/66acd000-77fe-1000-9115-d802423707d1/1033/screenlg1.jpg</fileUrl></image><image><displayOrder>2</displayOrder><imageMediaId>4F615410-4D5E-44E0-9580-71985AFE40F7</imageMediaId><imageMediaInstanceId>5138FE66-31DA-460B-A6DF-DAD30F20B7D2</imageMediaInstanceId><imageMediaType>14</imageMediaType><relationshipType>32</relationshipType><format>4</format><size>27</size><fileUrl>http://download.xbox.com/content/images/66acd000-77fe-1000-9115-d802423707d1/1033/screenlg2.jpg</fileUrl></image><image><displayOrder>3</displayOrder><imageMediaId>5F8794F0-ABCA-417D-98D4-873A685A6672</imageMediaId><imageMediaInstanceId>2C17C030-F121-4634-BAC5-1F8B1839952F</imageMediaInstanceId><imageMediaType>14</imageMediaType><relationshipType>32</relationshipType><format>4</format><size>27</size><fileUrl>http://download.xbox.com/content/images/66acd000-77fe-1000-9115-d802423707d1/1033/screenlg3.jpg</fileUrl></image><image><displayOrder>4</displayOrder><imageMediaId>82351028-8D8B-45BD-9DFE-77A771EE1E0E</imageMediaId><imageMediaInstanceId>B15F15EB-58AF-47E6-9E5C-2A55007A72BA</imageMediaInstanceId><imageMediaType>14</imageMediaType><relationshipType>32</relationshipType><format>4</format><size>27</size><fileUrl>http://download.xbox.com/content/images/66acd000-77fe-1000-9115-d802423707d1/1033/screenlg4.jpg</fileUrl></image><image><displayOrder>5</displayOrder><imageMediaId>4ED53B93-0822-48E6-BF6B-C64E5CC2F16C</imageMediaId><imageMediaInstanceId>90044606-90BC-4543-9AFF-CFDDF9BFBF1A</imageMediaInstanceId><imageMediaType>14</imageMediaType><relationshipType>32</relationshipType><format>4</format><size>27</size><fileUrl>http://download.xbox.com/content/images/66acd000-77fe-1000-9115-d802423707d1/1033/screenlg5.jpg</fileUrl></image><image><displayOrder>6</displayOrder><imageMediaId>44D25F5C-AAA8-4250-95E0-A6F5765E1BE3</imageMediaId><imageMediaInstanceId>E87C8DF9-0DB1-4424-9119-75E59A0E7A85</imageMediaInstanceId><imageMediaType>14</imageMediaType><relationshipType>32</relationshipType><format>4</format><size>27</size><fileUrl>http://download.xbox.com/content/images/66acd000-77fe-1000-9115-d802423707d1/1033/screenlg6.jpg</fileUrl></image></slideShow></slideShows><appTypeIds><appTypeId>2</appTypeId></appTypeIds><categories><category><categoryId>12030</categoryId><categoryName>Game Publisher Bit 30</categoryName><categorySystemId>12000</categorySystemId></category><category><categoryId>15001</categoryId><categoryName>App Categories</categoryName><categorySystemId>15000</categorySystemId></category><category><categoryId>15005</categoryId><categoryName>TV</categoryName><categorySystemId>15000</categorySystemId><parentCategoryId>15001</parentCategoryId></category></categories><showRating>false</showRating></a:entry></a:feed>