<?xml version="1.0" encoding="UTF-8"?> <a:feed xmlns:a="http://www.w3.org/2005/Atom" xmlns="http://marketplace.xboxlive.com/resource/product/v1"><a:author><a:name>Xbox LIVE</a:name></a:author><a:id>http://marketplace.xboxlive.com/resource/product/v1</a:id><a:title>Query Result</a:title><a:updated>2024-07-22 01:20:41Z</a:updated><totalItems>1</totalItems><numItems>1</numItems><locale>en-US</locale><a:entry itemNum="1" xmlns:a="http://www.w3.org/2005/Atom" xmlns="http://marketplace.xboxlive.com/resource/product/v1"><a:title>いっせーのせ！ONLINE</a:title><a:id>urn:uuid:66acd000-77fe-1000-9115-d802585503a3</a:id><a:updated>2017-10-10T13:21:20.903Z</a:updated><a:content>game content</a:content><offerInstances></offerInstances><productType>37</productType><reducedTitle>いっせーのせ！ONLINE</reducedTitle><reducedDescription>&quot;its say on set&quot; is an traditional hand game in Japan. Players lead own thumb up/down and an attacker expects to match the total number of thumbs. &quot;its-say-on-set&quot; is the call of that timing. Multiplayer mode supports up to 4 players by Xbox LIVE.</reducedDescription><fullTitle>Full Game - いっせーのせ！ONLINE</fullTitle><fullDescription>This game was classified by the community with the following category scores - Violence=0/3, Sex=0/3, Mature Content=0/3. &quot;its say on set&quot; is an traditional hand game in Japan. Players lead own thumb up/down and an attacker expects to match the total number of thumbs. &quot;its-say-on-set&quot; is the call of that timing. Multiplayer mode supports up to 4 players by Xbox LIVE.</fullDescription><visibilityDate>2017-10-10T13:21:05.857</visibilityDate><customGenre>Sports &amp; Recreation</customGenre><developerName>sasgames.jp</developerName><publisherName>sasgames.jp</publisherName><titleId>1481966499</titleId><hexTitleId>0x585503a3</hexTitleId><effectiveTitleId>1481508818</effectiveTitleId><gameReducedTitle>いっせーのせ！ONLINE</gameReducedTitle><userRating>2.75</userRating><numberOfRatings>99</numberOfRatings><gameCapabilities><offlinePlayersMin>1</offlinePlayersMin><offlinePlayersMax>1</offlinePlayersMax><offlineCoopHardDriveRequired>0</offlineCoopHardDriveRequired><offlineMaxHDTVModeId>1</offlineMaxHDTVModeId><offlineVoiceCommands>0</offlineVoiceCommands><offlinePeripheralCamera>0</offlinePeripheralCamera><offlineCustomSoundtracks>1</offlineCustomSoundtracks><offlineDolbyDigital>0</offlineDolbyDigital><onlineMultiplayerMin>2</onlineMultiplayerMin><onlineMultiplayerMax>4</onlineMultiplayerMax><onlineMultiplayerHardDriveRequired>0</onlineMultiplayerHardDriveRequired><onlineCoopHardDriveRequired>0</onlineCoopHardDriveRequired><onlineHardDriveRequired>0</onlineHardDriveRequired><onlineContentDownload>0</onlineContentDownload><onlineLeaderboards>0</onlineLeaderboards></gameCapabilities><images><image><imageMediaId>585503A3-0000-4000-8000-000000008004</imageMediaId><imageMediaInstanceId>DE8D532E-ECFB-470E-A473-00DF54AEDD99</imageMediaInstanceId><imageMediaType>14</imageMediaType><relationshipType>27</relationshipType><format>5</format><size>15</size><fileUrl>http://avatar.xboxlive.com/global/t.585503a3/marketplace/0/1</fileUrl><parentGameMediaId>66ACD000-77FE-1000-9115-D802585503A3</parentGameMediaId></image><image><imageMediaId>585503A3-0000-4001-8000-000100000000</imageMediaId><imageMediaInstanceId>9EC608F2-6167-4600-9501-36F1EDC343C2</imageMediaInstanceId><imageMediaType>14</imageMediaType><relationshipType>27</relationshipType><format>5</format><size>15</size><fileUrl>http://avatar.xboxlive.com/global/t.584e07d2/marketplace/0/585503a300000001</fileUrl><parentGameMediaId>66ACD000-77FE-1000-9115-D802585503A3</parentGameMediaId></image><image><imageMediaId>6A00C0F9-F0DD-4AA1-8C99-7B8952D9A8F4</imageMediaId><imageMediaInstanceId>E7C2A44C-D09A-4006-A132-503EA98EF7C7</imageMediaInstanceId><imageMediaType>14</imageMediaType><relationshipType>25</relationshipType><format>4</format><size>13</size><fileUrl>http://download.xbox.com:80/content/xna/assets/global/background.jpg</fileUrl><parentGameMediaId>66ACD000-77FE-1000-9115-D802585503A3</parentGameMediaId></image><image><imageMediaId>935EF46D-E44D-4071-9B02-7BB65E063D63</imageMediaId><imageMediaInstanceId>F102F3C5-E4B6-49D7-9325-65C47E7D1B77</imageMediaInstanceId><imageMediaType>14</imageMediaType><relationshipType>33</relationshipType><format>4</format><size>23</size><fileUrl>http://download.xbox.com:80/content/xna/assets/585503A3_World/xboxboxart.jpg</fileUrl><parentGameMediaId>66ACD000-77FE-1000-9115-D802585503A3</parentGameMediaId></image><image><imageMediaId>935EF46D-E44D-4071-9B02-7BB65E063D63</imageMediaId><imageMediaInstanceId>C018F177-1AA7-4E16-9D44-B447AECA2CF8</imageMediaInstanceId><imageMediaType>14</imageMediaType><relationshipType>33</relationshipType><format>4</format><size>30</size><fileUrl>http://download.xbox.com:80/content/xna/assets/585503A3_World/webboxart.jpg</fileUrl><parentGameMediaId>66ACD000-77FE-1000-9115-D802585503A3</parentGameMediaId></image><image><imageMediaId>585503A3-0000-4000-8000-000000008000</imageMediaId><imageMediaInstanceId>43548AAF-014E-43D0-811D-E7B863CCF555</imageMediaInstanceId><imageMediaType>14</imageMediaType><relationshipType>15</relationshipType><format>5</format><size>14</size><fileUrl>http://avatar.xboxlive.com/global/t.585503a3/icon/0/8000</fileUrl><parentGameMediaId>66ACD000-77FE-1000-9115-D802585503A3</parentGameMediaId></image></images><slideShows><slideShow><image><displayOrder>0</displayOrder><imageMediaId>E0F57908-36D3-475C-A8C7-C4E0837D0C88</imageMediaId><imageMediaInstanceId>7EF59806-73A5-4E26-AC3F-1C0107D8706F</imageMediaInstanceId><imageMediaType>14</imageMediaType><relationshipType>32</relationshipType><format>4</format><size>27</size><fileUrl>http://download.xbox.com:80/content/xna/assets/585503A3_World/screen2.jpg</fileUrl></image><image><displayOrder>0</displayOrder><imageMediaId>830F2FD0-9770-4CCE-A3F7-FA2048875D81</imageMediaId><imageMediaInstanceId>B612DB18-956B-43A8-913F-41B8A45A995B</imageMediaInstanceId><imageMediaType>14</imageMediaType><relationshipType>32</relationshipType><format>4</format><size>27</size><fileUrl>http://download.xbox.com:80/content/xna/assets/585503A3_World/screen4.jpg</fileUrl></image><image><displayOrder>0</displayOrder><imageMediaId>E51610F1-9A2C-4D8F-91EF-ED3EFE4EA3CB</imageMediaId><imageMediaInstanceId>3A331CC7-F239-46CC-BCD5-DF348F1D9307</imageMediaInstanceId><imageMediaType>14</imageMediaType><relationshipType>32</relationshipType><format>4</format><size>27</size><fileUrl>http://download.xbox.com:80/content/xna/assets/585503A3_World/screen1.jpg</fileUrl></image><image><displayOrder>0</displayOrder><imageMediaId>65E4BCAE-7A04-416C-8E3D-50378B180523</imageMediaId><imageMediaInstanceId>2583F48C-D78C-48D0-B945-EDE37D73A059</imageMediaInstanceId><imageMediaType>14</imageMediaType><relationshipType>32</relationshipType><format>4</format><size>27</size><fileUrl>http://download.xbox.com:80/content/xna/assets/585503A3_World/screen3.jpg</fileUrl></image></slideShow></slideShows><parentProducts><parentProduct><parentProductId>66acd000-77fe-1000-9115-d802585503a3</parentProductId><parentReducedTitle>いっせーのせ！ONLINE</parentReducedTitle><parentSortOrder>0</parentSortOrder></parentProduct></parentProducts><categories><category><categoryId>3000</categoryId><categoryName>Game Genres</categoryName><categorySystemId>3000</categorySystemId></category><category><categoryId>3013</categoryId><categoryName>Sports &amp; Recreation</categoryName><categorySystemId>3000</categorySystemId><parentCategoryId>3027</parentCategoryId></category><category><categoryId>3027</categoryId><categoryName>Xbox LIVE Games</categoryName><categorySystemId>3000</categorySystemId><parentCategoryId>3000</parentCategoryId></category><category><categoryId>4299</categoryId><categoryName>XNA Creators Club Games (XU)</categoryName><categorySystemId>4000</categorySystemId></category><category><categoryId>12001</categoryId><categoryName>Game Publisher Bit 1</categoryName><categorySystemId>12000</categorySystemId></category></categories></a:entry></a:feed>