<?xml version="1.0" encoding="UTF-8"?> <a:feed xmlns:a="http://www.w3.org/2005/Atom" xmlns="http://marketplace.xboxlive.com/resource/product/v1"><a:author><a:name>Xbox LIVE</a:name></a:author><a:id>http://marketplace.xboxlive.com/resource/product/v1</a:id><a:title>Query Result</a:title><a:updated>2024-07-22 00:22:38Z</a:updated><totalItems>1</totalItems><numItems>1</numItems><locale>en-US</locale><a:entry itemNum="1" xmlns:a="http://www.w3.org/2005/Atom" xmlns="http://marketplace.xboxlive.com/resource/product/v1"><a:title>GameTrailers</a:title><a:id>urn:uuid:66acd000-77fe-1000-9115-d802523207df</a:id><a:updated>2015-08-04T00:00:26.963Z</a:updated><a:content>game content</a:content><productType>61</productType><reducedTitle>GameTrailers</reducedTitle><reducedDescription>This is the best of GameTrailers all in one place! Watch all of your favorite GT Original shows, in-depth game reviews &amp; the newest game trailers.</reducedDescription><fullTitle>GameTrailers</fullTitle><fullDescription>This is the best of GameTrailers all in one place! Watch all of your favorite GT Original shows, in-depth game reviews &amp; the newest game previews / trailers in our new Xbox Live app. Whether you want to see the latest rant from the Angry Video Game Nerd, predictions from Michael Pachter or opinions from Geoff Keighley on the Bonus Round, we have you covered. Looking for the latest on newly released video games? Take a look at our library of trusted reviews available to you as soon as they hit the website.</fullDescription><voiceDisplayTitle>Game Trailers</voiceDisplayTitle><visibilityDate>2013-02-11T00:00:00</visibilityDate><globalOriginalReleaseDate>2013-03-12T00:00:00</globalOriginalReleaseDate><ratingId>0</ratingId><developerName>GameTrailers</developerName><publisherName>GameTrailers</publisherName><titleId>1379010527</titleId><hexTitleId>0x523207df</hexTitleId><productCapabilities><productCapability><capabilityInternalName>offlineMaxHDTVMode720p</capabilityInternalName><capabilityId>10</capabilityId><capabilityValue>True</capabilityValue></productCapability><productCapability><capabilityInternalName>offlineDolbyDigital</capabilityInternalName><capabilityId>30</capabilityId><capabilityValue>True</capabilityValue></productCapability></productCapabilities><images><image><imageMediaId>DC33BA37-6365-47C5-9326-071E573C4EBB</imageMediaId><imageMediaInstanceId>1AECCBBD-6214-464C-901C-04F7BF991168</imageMediaInstanceId><imageMediaType>14</imageMediaType><relationshipType>33</relationshipType><format>5</format><size>25</size><fileUrl>http://download.xbox.com/content/images/523207DF/en-us/tvposterlg.png</fileUrl><parentGameMediaId>66ACD000-77FE-1000-9115-D802523207DF</parentGameMediaId></image><image><imageMediaId>47D28636-C5C5-4410-91ED-6F4BC7451CDB</imageMediaId><imageMediaInstanceId>BEDCBE9A-037B-4229-9C9A-0E9A5FBF4E25</imageMediaInstanceId><imageMediaType>14</imageMediaType><relationshipType>22</relationshipType><format>5</format><size>44</size><fileUrl>http://download.xbox.com/content/images/66acd000-77fe-1000-9115-d802523207df/1033/tvposterlg.png</fileUrl><parentGameMediaId>66ACD000-77FE-1000-9115-D802523207DF</parentGameMediaId></image><image><imageMediaId>F6F70954-D84A-4634-9977-526E83BA05F3</imageMediaId><imageMediaInstanceId>771F4F37-66CA-44CE-ABA1-17B80F94911D</imageMediaInstanceId><imageMediaType>14</imageMediaType><relationshipType>33</relationshipType><format>5</format><size>45</size><fileUrl>http://download.xbox.com/content/images/523207DF/en-us/tvpostersm.png</fileUrl><parentGameMediaId>66ACD000-77FE-1000-9115-D802523207DF</parentGameMediaId></image><image><imageMediaId>0DACEB2C-A978-406A-A4A9-F33495DDD0D0</imageMediaId><imageMediaInstanceId>93B93EDA-D73E-42BA-B142-5C0E0392B7E8</imageMediaInstanceId><imageMediaType>14</imageMediaType><relationshipType>33</relationshipType><format>4</format><size>30</size><fileUrl>http://download.xbox.com/content/images/66acd000-77fe-1000-9115-d802523207df/1033/boxartsm.jpg</fileUrl><parentGameMediaId>66ACD000-77FE-1000-9115-D802523207DF</parentGameMediaId></image><image><imageMediaId>B6A485C1-4473-43CB-AF45-5B81DC079402</imageMediaId><imageMediaInstanceId>61557849-B95B-406B-9927-7EFC8B8E21EA</imageMediaInstanceId><imageMediaType>14</imageMediaType><relationshipType>27</relationshipType><format>5</format><size>15</size><fileUrl>http://download.xbox.com/content/images/66acd000-77fe-1000-9115-d802523207df/1033/banner.png</fileUrl><parentGameMediaId>66ACD000-77FE-1000-9115-D802523207DF</parentGameMediaId></image><image><imageMediaId>F81D9B4C-DF42-4C7F-AFBC-7CC98F247C83</imageMediaId><imageMediaInstanceId>FFCCC519-113E-4E1A-BF7F-B37F8142C825</imageMediaInstanceId><imageMediaType>14</imageMediaType><relationshipType>33</relationshipType><format>4</format><size>23</size><fileUrl>http://download.xbox.com/content/images/66acd000-77fe-1000-9115-d802523207df/1033/boxartlg.jpg</fileUrl><parentGameMediaId>66ACD000-77FE-1000-9115-D802523207DF</parentGameMediaId></image><image><imageMediaId>5B63F6A4-ABB2-48FD-B474-1DC2F3C7967B</imageMediaId><imageMediaInstanceId>1694DA51-0FE9-4735-94E9-C56667628AE8</imageMediaInstanceId><imageMediaType>14</imageMediaType><relationshipType>23</relationshipType><format>5</format><size>14</size><fileUrl>http://download.xbox.com/content/images/66acd000-77fe-1000-9115-d802523207df/1033/tile.png</fileUrl><parentGameMediaId>66ACD000-77FE-1000-9115-D802523207DF</parentGameMediaId></image><image><imageMediaId>F19B996D-9399-4654-AF22-7D40AE88316A</imageMediaId><imageMediaInstanceId>900F1479-140C-4B02-8FC3-F22F7700E748</imageMediaInstanceId><imageMediaType>14</imageMediaType><relationshipType>33</relationshipType><format>4</format><size>46</size><fileUrl>http://download.xbox.com/content/images/66acd000-77fe-1000-9115-d802523207df/1033/providerlogo.jpg</fileUrl><parentGameMediaId>66ACD000-77FE-1000-9115-D802523207DF</parentGameMediaId></image><image><imageMediaId>CDF7F008-AA00-4B8C-9DC1-3B8E13EF6E8F</imageMediaId><imageMediaInstanceId>8D9548D4-B5EE-4F08-9B1E-F40F2C6A9CBE</imageMediaInstanceId><imageMediaType>14</imageMediaType><relationshipType>25</relationshipType><format>4</format><size>22</size><fileUrl>http://download.xbox.com/content/images/66acd000-77fe-1000-9115-d802523207df/1033/background.jpg</fileUrl><parentGameMediaId>66ACD000-77FE-1000-9115-D802523207DF</parentGameMediaId></image></images><appTypeIds><appTypeId>1</appTypeId></appTypeIds><categories><category><categoryId>12001</categoryId><categoryName>Game Publisher Bit 1</categoryName><categorySystemId>12000</categorySystemId></category><category><categoryId>15001</categoryId><categoryName>App Categories</categoryName><categorySystemId>15000</categorySystemId></category><category><categoryId>15003</categoryId><categoryName>Video</categoryName><categorySystemId>15000</categorySystemId><parentCategoryId>15001</parentCategoryId></category></categories><showRating>false</showRating></a:entry></a:feed>