<?xml version="1.0" encoding="UTF-8"?> <a:feed xmlns:a="http://www.w3.org/2005/Atom" xmlns="http://marketplace.xboxlive.com/resource/product/v1"><a:author><a:name>Xbox LIVE</a:name></a:author><a:id>http://marketplace.xboxlive.com/resource/product/v1</a:id><a:title>Query Result</a:title><a:updated>2024-07-20 14:23:37Z</a:updated><totalItems>1</totalItems><numItems>1</numItems><locale>en-US</locale><a:entry itemNum="1" xmlns:a="http://www.w3.org/2005/Atom" xmlns="http://marketplace.xboxlive.com/resource/product/v1"><a:title>Ben 10™ Galactic Racing</a:title><a:id>urn:uuid:66acd000-77fe-1000-9115-d802445007fc</a:id><a:updated>2016-09-05T02:55:09.757Z</a:updated><a:content>game content</a:content><offerInstances></offerInstances><productType>1</productType><reducedTitle>Ben 10™ Galactic Racing</reducedTitle><reducedDescription>Ben 10 Galactic Racing, the first and only kart racing game based on the hit Ben 10 television series on Cartoon Network, features Ben and his alien heroes competing in an over-the-top, galactic grand prix race in over 25 exhilarating tracks spread across five massive worlds! Play as either Ben, Kevin or choose from 13 fan-favorite aliens and equip them in more than 30 unique karts. Compete for the best times in the high-speed grand prix modes or engage in four-player multiplayer mayhem!</reducedDescription><fullTitle>Ben 10™ Galactic Racing</fullTitle><fullDescription>The Games on Demand version supports English, French, Italian, German and Spanish. Download the manual for this game by locating the game on http://marketplace.xbox.com and selecting “See Game Manual&quot;. In Ben 10 Galactic Racing, the first and only racing game based on the popular Ben 10 television series on Cartoon Network, fans will enjoy a Ben 10 multiplayer experience like never before in a galactic grand prix filled with surprises at every turn. Ben 10 Galactic Racing features over 25 exhilarating and challenging tracks spread across five massive worlds from the Ben 10 universe. Play as either Ben, Kevin or choose from 13 fan-favorite aliens and equip them in more than 30 unique karts. Ben 10 Galactic Racing presents the ultimate racing experience this fall, where every character has a special ability to utilize on the race track and even Ben can transform into different aliens mid-race!</fullDescription><voiceDisplayTitle>Ben 10 Galactic Racing</voiceDisplayTitle><visibilityDate>2011-10-07T00:00:00</visibilityDate><globalOriginalReleaseDate>2011-10-18T00:00:00</globalOriginalReleaseDate><countryReleaseDate>2011-10-18T00:00:00</countryReleaseDate><ratingId>10</ratingId><ratingDescriptors><ratingDescriptor level="1.0000">5</ratingDescriptor><ratingDescriptor level="1.0000">37</ratingDescriptor></ratingDescriptors><developerName>Monkey Bar Games</developerName><publisherName>D3Publisher of America, Inc.</publisherName><titleId>1146095612</titleId><hexTitleId>0x445007fc</hexTitleId><effectiveTitleId>1146095612</effectiveTitleId><gameReducedTitle>Ben 10™ Galactic Racing</gameReducedTitle><userRating>3.50</userRating><numberOfRatings>4334</numberOfRatings><gameCapabilities><offlinePlayersMin>1</offlinePlayersMin><offlinePlayersMax>4</offlinePlayersMax><offlineCoopPlayersMin>2</offlineCoopPlayersMin><offlineCoopPlayersMax>4</offlineCoopPlayersMax><offlineMaxHDTVModeId>1</offlineMaxHDTVModeId><offlineDolbyDigital>1</offlineDolbyDigital></gameCapabilities><images><image><imageMediaId>A0A1B05A-4994-463E-B141-5AE92DB63848</imageMediaId><imageMediaInstanceId>F9BA9B01-57B9-49DC-929A-05C939A7CA1A</imageMediaInstanceId><imageMediaType>14</imageMediaType><relationshipType>33</relationshipType><format>4</format><size>23</size><fileUrl>http://download.xbox.com/content/images/66acd000-77fe-1000-9115-d802445007fc/1033/boxartlg.jpg</fileUrl><parentGameMediaId>66ACD000-77FE-1000-9115-D802445007FC</parentGameMediaId></image><image><imageMediaId>191CADEF-B2D8-4437-B33B-4927E323C27F</imageMediaId><imageMediaInstanceId>DD347412-8724-4998-A3CA-100B0C4FEAF9</imageMediaInstanceId><imageMediaType>14</imageMediaType><relationshipType>27</relationshipType><format>5</format><size>15</size><fileUrl>http://download.xbox.com/content/images/66acd000-77fe-1000-9115-d802445007fc/1033/banner.png</fileUrl><parentGameMediaId>66ACD000-77FE-1000-9115-D802445007FC</parentGameMediaId></image><image><imageMediaId>6285ED89-0451-4276-B2D4-2EC0E6E43AFF</imageMediaId><imageMediaInstanceId>FE1941AF-B9E1-4BCA-9BBB-11CE89C12378</imageMediaInstanceId><imageMediaType>14</imageMediaType><relationshipType>25</relationshipType><format>4</format><size>22</size><fileUrl>http://download.xbox.com/content/images/66acd000-77fe-1000-9115-d802445007fc/1033/background.jpg</fileUrl><parentGameMediaId>66ACD000-77FE-1000-9115-D802445007FC</parentGameMediaId></image><image><imageMediaId>AF9D3422-D983-4A65-978B-996AAE2C5119</imageMediaId><imageMediaInstanceId>9881CBFD-770B-4416-AA45-45136D387B91</imageMediaInstanceId><imageMediaType>14</imageMediaType><relationshipType>33</relationshipType><format>4</format><size>30</size><fileUrl>http://download.xbox.com/content/images/66acd000-77fe-1000-9115-d802445007fc/1033/boxartsm.jpg</fileUrl><parentGameMediaId>66ACD000-77FE-1000-9115-D802445007FC</parentGameMediaId></image><image><imageMediaId>A72B7DCF-CAEF-4095-8314-6DBB3128B72E</imageMediaId><imageMediaInstanceId>0542D541-F413-4594-BEF9-5CFD2D370AB8</imageMediaInstanceId><imageMediaType>14</imageMediaType><relationshipType>23</relationshipType><format>5</format><size>14</size><fileUrl>http://download.xbox.com/content/images/66acd000-77fe-1000-9115-d802445007fc/1033/tile.png</fileUrl><parentGameMediaId>66ACD000-77FE-1000-9115-D802445007FC</parentGameMediaId></image></images><slideShows><slideShow><image><displayOrder>1</displayOrder><imageMediaId>D92FB4E9-D894-41C2-8A86-2B2B723E183C</imageMediaId><imageMediaInstanceId>5FB48491-511D-489E-ACE3-F7870A6B6392</imageMediaInstanceId><imageMediaType>14</imageMediaType><relationshipType>32</relationshipType><format>4</format><size>27</size><fileUrl>http://download.xbox.com/content/images/66acd000-77fe-1000-9115-d802445007fc/1033/screenlg1.jpg</fileUrl></image><image><displayOrder>2</displayOrder><imageMediaId>3CCB60D3-EE62-4CC0-A595-3AF412F07515</imageMediaId><imageMediaInstanceId>A5AD265A-8F9E-44AD-A04F-05E2177888A7</imageMediaInstanceId><imageMediaType>14</imageMediaType><relationshipType>32</relationshipType><format>4</format><size>27</size><fileUrl>http://download.xbox.com/content/images/66acd000-77fe-1000-9115-d802445007fc/1033/screenlg2.jpg</fileUrl></image><image><displayOrder>3</displayOrder><imageMediaId>3F765BF4-BB85-4E80-8626-9CB2A7925717</imageMediaId><imageMediaInstanceId>2A9264B7-3F06-4200-AF31-5786F1A7CC09</imageMediaInstanceId><imageMediaType>14</imageMediaType><relationshipType>32</relationshipType><format>4</format><size>27</size><fileUrl>http://download.xbox.com/content/images/66acd000-77fe-1000-9115-d802445007fc/1033/screenlg3.jpg</fileUrl></image><image><displayOrder>4</displayOrder><imageMediaId>9043F63C-E623-46FA-A8EC-C8529FF3BBF8</imageMediaId><imageMediaInstanceId>1888E92C-10A6-4B9F-B8E3-363131D0968D</imageMediaInstanceId><imageMediaType>14</imageMediaType><relationshipType>32</relationshipType><format>4</format><size>27</size><fileUrl>http://download.xbox.com/content/images/66acd000-77fe-1000-9115-d802445007fc/1033/screenlg4.jpg</fileUrl></image><image><displayOrder>5</displayOrder><imageMediaId>83D7D634-A4EB-4A51-BA75-DD4BE9F91599</imageMediaId><imageMediaInstanceId>4F220097-776C-456F-8117-56BF6CBEE3F4</imageMediaInstanceId><imageMediaType>14</imageMediaType><relationshipType>32</relationshipType><format>4</format><size>27</size><fileUrl>http://download.xbox.com/content/images/66acd000-77fe-1000-9115-d802445007fc/1033/screenlg5.jpg</fileUrl></image><image><displayOrder>6</displayOrder><imageMediaId>41C2D301-2723-4562-B280-7D594192EEC2</imageMediaId><imageMediaInstanceId>A69D5ED0-A733-4E8E-873E-5325A475F797</imageMediaInstanceId><imageMediaType>14</imageMediaType><relationshipType>32</relationshipType><format>4</format><size>27</size><fileUrl>http://download.xbox.com/content/images/66acd000-77fe-1000-9115-d802445007fc/1033/screenlg6.jpg</fileUrl></image><image><displayOrder>7</displayOrder><imageMediaId>3C3C5911-E618-4A55-B942-F0D383CCCB63</imageMediaId><imageMediaInstanceId>7BFCA5F2-CF97-410A-A093-7A57D32A563B</imageMediaInstanceId><imageMediaType>14</imageMediaType><relationshipType>32</relationshipType><format>4</format><size>27</size><fileUrl>http://download.xbox.com/content/images/66acd000-77fe-1000-9115-d802445007fc/1033/screenlg7.jpg</fileUrl></image><image><displayOrder>8</displayOrder><imageMediaId>B35C3897-015B-4FA9-BBD4-D03C530DD37F</imageMediaId><imageMediaInstanceId>D9473D55-105D-4CED-B652-63D8D32127D0</imageMediaInstanceId><imageMediaType>14</imageMediaType><relationshipType>32</relationshipType><format>4</format><size>27</size><fileUrl>http://download.xbox.com/content/images/66acd000-77fe-1000-9115-d802445007fc/1033/screenlg8.jpg</fileUrl></image><image><displayOrder>9</displayOrder><imageMediaId>36C047F3-BC7E-41ED-A165-BD1ECF38EDC8</imageMediaId><imageMediaInstanceId>D4250DCB-109A-4044-8292-0801995B325F</imageMediaInstanceId><imageMediaType>14</imageMediaType><relationshipType>32</relationshipType><format>4</format><size>27</size><fileUrl>http://download.xbox.com/content/images/66acd000-77fe-1000-9115-d802445007fc/1033/screenlg9.jpg</fileUrl></image><image><displayOrder>10</displayOrder><imageMediaId>D50013CB-9424-465B-A173-43D0DD0F5799</imageMediaId><imageMediaInstanceId>87B34D61-785B-4C20-ADC4-223E0B6736A2</imageMediaInstanceId><imageMediaType>14</imageMediaType><relationshipType>32</relationshipType><format>4</format><size>27</size><fileUrl>http://download.xbox.com/content/images/66acd000-77fe-1000-9115-d802445007fc/1033/screenlg10.jpg</fileUrl></image><image><displayOrder>11</displayOrder><imageMediaId>FF5B23FD-2051-41FA-8DC5-A16BBBD5D55D</imageMediaId><imageMediaInstanceId>673B3376-FFC2-4134-BF0C-75C8C3358157</imageMediaInstanceId><imageMediaType>14</imageMediaType><relationshipType>32</relationshipType><format>4</format><size>27</size><fileUrl>http://download.xbox.com/content/images/66acd000-77fe-1000-9115-d802445007fc/1033/screenlg11.jpg</fileUrl></image><image><displayOrder>12</displayOrder><imageMediaId>8B0BF272-5032-4125-8736-5AAFFD391AA8</imageMediaId><imageMediaInstanceId>A5D5A9ED-765F-463F-9856-8356D4C5C54B</imageMediaInstanceId><imageMediaType>14</imageMediaType><relationshipType>32</relationshipType><format>4</format><size>27</size><fileUrl>http://download.xbox.com/content/images/66acd000-77fe-1000-9115-d802445007fc/1033/screenlg12.jpg</fileUrl></image><image><displayOrder>13</displayOrder><imageMediaId>C0384D51-5AB3-4BB4-B529-A127401EF2C9</imageMediaId><imageMediaInstanceId>CDEF1B3F-2ABE-40A0-99A5-150F53B59FD8</imageMediaInstanceId><imageMediaType>14</imageMediaType><relationshipType>32</relationshipType><format>4</format><size>27</size><fileUrl>http://download.xbox.com/content/images/66acd000-77fe-1000-9115-d802445007fc/1033/screenlg13.jpg</fileUrl></image></slideShow></slideShows><parentProducts><parentProduct><parentProductId>66acd000-77fe-1000-9115-d802445007fc</parentProductId><parentReducedTitle>Ben 10™ Galactic Racing</parentReducedTitle><parentSortOrder>0</parentSortOrder></parentProduct></parentProducts><relatedUrls><relatedUrl><relatedUrlType>3</relatedUrlType><relatedUrl>http://download.xbox.com/content/445007fc/Ben10GR_360_ManualGuts_NONPRINTED_FINAL.pdf</relatedUrl></relatedUrl></relatedUrls><categories><category><categoryId>3000</categoryId><categoryName>Game Genres</categoryName><categorySystemId>3000</categorySystemId></category><category><categoryId>3005</categoryId><categoryName>Family</categoryName><categorySystemId>3000</categorySystemId><parentCategoryId>3027</parentCategoryId></category><category><categoryId>3009</categoryId><categoryName>Racing &amp; Flying</categoryName><categorySystemId>3000</categorySystemId><parentCategoryId>3027</parentCategoryId></category><category><categoryId>3027</categoryId><categoryName>Xbox LIVE Games</categoryName><categorySystemId>3000</categorySystemId><parentCategoryId>3000</parentCategoryId></category></categories></a:entry></a:feed>