<?xml version="1.0" encoding="UTF-8"?> <a:feed xmlns:a="http://www.w3.org/2005/Atom" xmlns="http://marketplace.xboxlive.com/resource/product/v1"><a:author><a:name>Xbox LIVE</a:name></a:author><a:id>http://marketplace.xboxlive.com/resource/product/v1</a:id><a:title>Query Result</a:title><a:updated>2024-07-22 02:55:49Z</a:updated><totalItems>1</totalItems><numItems>1</numItems><locale>en-US</locale><a:entry itemNum="1" xmlns:a="http://www.w3.org/2005/Atom" xmlns="http://marketplace.xboxlive.com/resource/product/v1"><a:title>Visa - go</a:title><a:id>urn:uuid:66acd000-77fe-1000-9115-d80258570868</a:id><a:updated>2014-03-17T18:37:35.987Z</a:updated><a:content>game content</a:content><productType>46</productType><reducedTitle>Visa - go</reducedTitle><reducedDescription>Visa will give you an additional 300 points to use on Xbox for FREE!  Microsoft Points can be used to buy Games on Demand, Game Add-ons, Arcade Title, HD movies and TV downloads or in the new Avatar Marketplace. Microsoft Points may be used towards Xbox content and merchandise on Xbox LIVE or Xbox.com. Xbox Live Gold or Silver membership registration required. Terms and Conditions: Free Microsoft Points Gift Offer available between 9/1/09 and 9/30/09 to Xbox Live Gold or Silver Account holders …</reducedDescription><fullTitle>Visa - go</fullTitle><fullDescription>Visa will give you an additional 300 points to use on Xbox for FREE!  Microsoft Points can be used to buy Games on Demand, Game Add-ons, Arcade Title, HD movies and TV downloads or in the new Avatar Marketplace. Microsoft Points may be used towards Xbox content and merchandise on Xbox LIVE or Xbox.com. Xbox Live Gold or Silver membership registration required. Terms and Conditions: Free Microsoft Points Gift Offer available between 9/1/09 and 9/30/09 to Xbox Live Gold or Silver Account holders in good standing, who buy 2000 or more Microsoft points with their Visa card. Microsoft Points are non-transferrable and are subject to the terms and conditions of the Microsoft Points program.   Microsoft Promotional Points codes must be redeemed by 11:59:59 pm ET on 6/30/2010.   Microsoft Promotion Points codes that are not redeemed by 11:59:59 pm ET on 6/30/2010 are void.  All selections will be conducted under the supervision of Sponsor (Microsoft), whose decisions are final. No substitution, transfer, or assignment permitted, except that Sponsor reserves the right to substitute a Gift of equal or greater value. Taxes on the Gift Offer are solely the responsibility of the recipients. Sponsor is not responsible for technical errors of any kind, including software or network transmission errors. Offer valid to individual customers, limit [1] per Xbox Live account. Microsoft Points are subject to the terms and conditions set by Microsoft Corporation. See www.xbox.com/en-US/live/microsoftpoints.htm for details regarding Microsoft Points program. Microsoft Points have no cash value and cannot be substituted or exchanged for cash.</fullDescription><visibilityDate>2009-08-26T00:23:52.467</visibilityDate><retailMSRP>0.0000</retailMSRP><customGenre>Visa - go</customGenre><developerName>Visa - go</developerName><publisherName>Visa - go</publisherName><titleId>1482098792</titleId><hexTitleId>0x58570868</hexTitleId><gameCapabilities/><images><image><imageMediaId>58570868-0000-4002-8000-000000000001</imageMediaId><imageMediaInstanceId>58570868-0000-4002-8000-000004090001</imageMediaInstanceId><imageMediaType>14</imageMediaType><relationshipType>33</relationshipType><format>4</format><size>30</size><fileUrl>http://mktplassets.xbox.com/NR/rdonlyres/E13C0961-ED58-4987-936D-D1ECA9803976/0/boxvisago.jpg</fileUrl><parentGameMediaId>66ACD000-77FE-1000-9115-D80258570868</parentGameMediaId></image><image><imageMediaId>58570868-0000-4002-8000-000000000002</imageMediaId><imageMediaInstanceId>58570868-0000-4002-8000-000004090002</imageMediaInstanceId><imageMediaType>14</imageMediaType><relationshipType>33</relationshipType><format>4</format><size>23</size><fileUrl>http://mktplassets.xbox.com/NR/rdonlyres/DAA8D01D-9C92-4168-B242-FB9CAA25408C/0/cboxvisago.jpg</fileUrl><parentGameMediaId>66ACD000-77FE-1000-9115-D80258570868</parentGameMediaId></image><image><imageMediaId>58570868-0000-4002-8000-000000000003</imageMediaId><imageMediaInstanceId>58570868-0000-4002-8000-000004090003</imageMediaInstanceId><imageMediaType>14</imageMediaType><relationshipType>25</relationshipType><format>4</format><size>22</size><fileUrl>http://mktplassets.xbox.com/NR/rdonlyres/ECF5A1C6-6AF7-434C-A5CF-7C94D136C284/0/cbackvisago.jpg</fileUrl><parentGameMediaId>66ACD000-77FE-1000-9115-D80258570868</parentGameMediaId></image><image><imageMediaId>58570868-0000-4000-8000-000000008004</imageMediaId><imageMediaInstanceId>4E4166A5-C4EA-4722-B19B-9585CFD877DC</imageMediaInstanceId><imageMediaType>14</imageMediaType><relationshipType>27</relationshipType><format>5</format><size>15</size><fileUrl>http://avatar.xboxlive.com/global/t.58570868/marketplace/0/1</fileUrl><parentGameMediaId>66ACD000-77FE-1000-9115-D80258570868</parentGameMediaId></image><image><imageMediaId>58570868-0000-4000-8000-000000008000</imageMediaId><imageMediaInstanceId>57E98B4B-006D-478B-94C5-D604B8E7A3FA</imageMediaInstanceId><imageMediaType>14</imageMediaType><relationshipType>15</relationshipType><format>5</format><size>14</size><fileUrl>http://avatar.xboxlive.com/global/t.58570868/icon/0/8000</fileUrl><parentGameMediaId>66ACD000-77FE-1000-9115-D80258570868</parentGameMediaId></image></images><categories><category><categoryId>3000</categoryId><categoryName>Game Genres</categoryName><categorySystemId>3000</categorySystemId></category><category><categoryId>3025</categoryId><categoryName>Xbox LIVE Marketplace</categoryName><categorySystemId>3000</categorySystemId><parentCategoryId>3000</parentCategoryId></category><category><categoryId>3312</categoryId><categoryName>Independent &amp; Music Videos</categoryName><categorySystemId>3000</categorySystemId><parentCategoryId>3025</parentCategoryId></category><category><categoryId>3314</categoryId><categoryName>Music and Short Videos</categoryName><categorySystemId>3000</categorySystemId><parentCategoryId>3312</parentCategoryId></category><category><categoryId>3318</categoryId><categoryName>More Entertainment</categoryName><categorySystemId>3000</categorySystemId><parentCategoryId>3314</parentCategoryId></category><category><categoryId>4301</categoryId><categoryName>Xbox LIVE</categoryName><categorySystemId>4000</categorySystemId></category></categories></a:entry></a:feed>